src/mutsumi/role.py
src/mutsumi/tool_set.py
src/mutsumi/deepseek/__init__.py
src/mutsumi/deepseek/context.py
src/mutsumi/deepseek/deepseek.py
src/mutsumi/deepseek/logger.py
mutsumi-0.1.0.dist-info/METADATA
mutsumi-0.1.0.dist-info/WHEEL
mutsumi-0.1.0.dist-info/licenses/LICENSE
mutsumi-0.1.0.dist-info/RECORD
