Metadata-Version: 2.4
Name: mutsumi
Version: 0.1.0
Summary: An AI agent develop frame based on openai SDK.
License-File: LICENSE
Requires-Python: >=3.13
Requires-Dist: openai>=1.106.1
Requires-Dist: pyreadline>=2.1
Requires-Dist: rich>=14.1.0
Requires-Dist: tl-emailtools>=1.1.1
